codesleuth/__init__.py
codesleuth/api.py
codesleuth/config.py
codesleuth/indexing/__init__.py
codesleuth/indexing/parser.py
codesleuth/indexing/semantic_index.py
codesleuth/search/__init__.py
codesleuth/search/lexical_search.py
codesleuth/search/semantic_search.py
codesleuth-0.1.1.dist-info/LICENSE
codesleuth-0.1.1.dist-info/METADATA
codesleuth-0.1.1.dist-info/WHEEL
codesleuth-0.1.1.dist-info/RECORD
