Metadata-Version: 2.3
Name: codesleuth
Version: 0.1.1
Summary: CodeSleuth is a local-first code search and retrieval tool optimized for LLM integration
Keywords: code search,semantic search,code retrieval,local-first,llm integration,mlx,faiss,embeddings,tree-sitter,developer tools,code understanding,code intelligence,code assistant,apple silicon,arm optimization,vector search,semantic indexing
Author: Jack Nam
Author-email: naminalstack+codesleuth@gmail.com
Requires-Python: >=3.10,<4.0
Classifier: Development Status :: 3 - Alpha
Classifier: Intended Audience :: Developers
Classifier: License :: OSI Approved :: MIT License
Classifier: Programming Language :: Python :: 3
Classifier: Programming Language :: Python :: 3.10
Classifier: Programming Language :: Python :: 3.11
Classifier: Programming Language :: Python :: 3.12
Classifier: Topic :: Software Development :: Libraries :: Python Modules
Requires-Dist: faiss-cpu (>=1.10.0,<2.0.0)
Requires-Dist: loguru (>=0.7.3,<0.8.0)
Requires-Dist: numpy (>=2.2.4,<3.0.0)
Requires-Dist: pydantic (>=2.11.0,<3.0.0)
Requires-Dist: torch (>=2.6.0,<3.0.0)
Requires-Dist: tqdm (>=4.67.1,<5.0.0)
Requires-Dist: transformers (>=4.50.2,<5.0.0)
Requires-Dist: tree-sitter (>=0.24.0,<0.25.0)
Requires-Dist: tree-sitter-language-pack (>=0.6.1,<0.7.0)
